closest_pairs/__init__.py
closest_pairs/main.py
closest_pairs-0.1.5.dist-info/LICENSE
closest_pairs-0.1.5.dist-info/METADATA
closest_pairs-0.1.5.dist-info/WHEEL
closest_pairs-0.1.5.dist-info/top_level.txt
closest_pairs-0.1.5.dist-info/RECORD
