Metadata-Version: 2.1
Name: closest-pairs
Version: 0.1.5
Summary: closest_pairs finds the closest pairs of points in a dataset
Home-page: https://github.com/justinshenk/closest_pairs
Author: Justin Shenk
Author-email: shenkjustin@gmail.com
License: MIT
Keywords: mathematics geometry
Platform: UNKNOWN
Classifier: Intended Audience :: Developers
Classifier: License :: OSI Approved :: MIT License
Classifier: Intended Audience :: Education
Classifier: Intended Audience :: Science/Research
Classifier: Programming Language :: Python :: 3
Classifier: Programming Language :: Python :: 3.6
Classifier: Topic :: Scientific/Engineering :: Mathematics
Classifier: Topic :: Software Development :: Libraries :: Python Modules
Classifier: Topic :: Software Development :: Libraries
Requires-Python: >= 3.6
Requires-Dist: numpy
Requires-Dist: scikit-learn
